watchsync/__init__.py
watchsync/__main__.py
watchsync/__version__.py
watchsync/command.py
watchsync/commands/__init__.py
watchsync/commands/file_add.py
watchsync/commands/file_del.py
watchsync/commands/file_list.py
watchsync/commands/file_sync.py
watchsync/commands/help_list.py
watchsync/commands/reload.py
watchsync/commands/start.py
watchsync/commands/status.py
watchsync/commands/stop.py
watchsync/commands/storage_add.py
watchsync/commands/storage_del.py
watchsync/commands/storage_list.py
watchsync/commands/version.py
watchsync/config.py
watchsync/daemon/__init__.py
watchsync/daemon/connector.py
watchsync/daemon/server_ssh.py
watchsync/daemon/watchsyncd.py
watchsync/daemon/watchsyncd_event_handler.py
watchsync/daemon/watchsyncd_observer.py
watchsync/logger.py
watchsync/utils.py
watchsync-0.1.2.dist-info/LICENSE
watchsync-0.1.2.dist-info/METADATA
watchsync-0.1.2.dist-info/WHEEL
watchsync-0.1.2.dist-info/entry_points.txt
watchsync-0.1.2.dist-info/RECORD
