Metadata-Version: 2.1
Name: watchsync
Version: 0.1.2
Summary: A Python-based tool for real-time file monitoring and synchronization, designed to replicate changes between local or remote locations.
Home-page: https://github.com/rlizana/watchsync
License: AGPL-3.0
Keywords: rsync,watchdog,real-time,synchronization,watchfiles,sync,inotify,file monitoring,file synchronization,file replication,file sync,file watcher
Author: Roberto Lizana
Author-email: rober.lizana@gmail.com
Requires-Python: >=3.12,<4.0
Classifier: License :: OSI Approved :: GNU Affero General Public License v3
Classifier: Programming Language :: Python :: 3
Classifier: Programming Language :: Python :: 3.12
Requires-Dist: cleo (>=2.1.0,<3.0.0)
Requires-Dist: pyyaml (>=6.0.2,<7.0.0)
Requires-Dist: watchdog (>=6.0.0,<7.0.0)
Project-URL: Repository, https://github.com/rlizana/watchsync
